buildbot_slave-0.9.0b9.data/scripts/buildslave
buildbot_slave-0.9.0b9.dist-info/DESCRIPTION.rst
buildbot_slave-0.9.0b9.dist-info/METADATA
buildbot_slave-0.9.0b9.dist-info/RECORD
buildbot_slave-0.9.0b9.dist-info/WHEEL
buildbot_slave-0.9.0b9.dist-info/metadata.json
buildbot_slave-0.9.0b9.dist-info/pbr.json
buildbot_slave-0.9.0b9.dist-info/top_level.txt
buildslave/VERSION
buildslave/__init__.py
buildslave/base.py
buildslave/bot.py
buildslave/exceptions.py
buildslave/interfaces.py
buildslave/null.py
buildslave/pb.py
buildslave/pbutil.py
buildslave/runprocess.py
buildslave/util.py
buildslave/commands/__init__.py
buildslave/commands/base.py
buildslave/commands/fs.py
buildslave/commands/registry.py
buildslave/commands/removed.py
buildslave/commands/repo.py
buildslave/commands/shell.py
buildslave/commands/transfer.py
buildslave/commands/utils.py
buildslave/monkeypatches/__init__.py
buildslave/monkeypatches/bug4881.py
buildslave/monkeypatches/bug5079.py
buildslave/monkeypatches/testcase_assert.py
buildslave/scripts/__init__.py
buildslave/scripts/base.py
buildslave/scripts/create_slave.py
buildslave/scripts/logwatcher.py
buildslave/scripts/restart.py
buildslave/scripts/runner.py
buildslave/scripts/start.py
buildslave/scripts/stop.py
buildslave/scripts/upgrade_slave.py
buildslave/test/__init__.py
buildslave/test/test_extra_coverage.py
buildslave/test/fake/__init__.py
buildslave/test/fake/remote.py
buildslave/test/fake/runprocess.py
buildslave/test/fake/slavebuilder.py
buildslave/test/unit/__init__.py
buildslave/test/unit/runprocess-scripts.py
buildslave/test/unit/test_bot.py
buildslave/test/unit/test_bot_BuildSlave.py
buildslave/test/unit/test_commands_base.py
buildslave/test/unit/test_commands_fs.py
buildslave/test/unit/test_commands_registry.py
buildslave/test/unit/test_commands_shell.py
buildslave/test/unit/test_commands_transfer.py
buildslave/test/unit/test_commands_utils.py
buildslave/test/unit/test_runprocess.py
buildslave/test/unit/test_scripts_base.py
buildslave/test/unit/test_scripts_create_slave.py
buildslave/test/unit/test_scripts_restart.py
buildslave/test/unit/test_scripts_runner.py
buildslave/test/unit/test_scripts_start.py
buildslave/test/unit/test_scripts_stop.py
