Metadata-Version: 2.0
Name: buildbot-slave
Version: 0.9.0b9
Summary: Buildbot Slave Daemon
Home-page: http://buildbot.net/
Author: Dustin J. Mitchell
Author-email: dustin@v.igoro.us
License: GNU GPL
Platform: UNKNOWN
Classifier: Development Status :: 5 - Production/Stable
Classifier: Environment :: No Input/Output (Daemon)
Classifier: Intended Audience :: Developers
Classifier: License :: OSI Approved :: GNU General Public License (GPL)
Classifier: Topic :: Software Development :: Build Tools
Classifier: Topic :: Software Development :: Testing
Requires-Dist: future
Requires-Dist: twisted (>=8.0.0)
Provides-Extra: test
Requires-Dist: mock; extra == 'test'
Requires-Dist: pep8; extra == 'test'
Requires-Dist: pyflakes; extra == 'test'
Requires-Dist: pylint (==1.1.0); extra == 'test'
Requires-Dist: setuptools-trial; extra == 'test'
